wired/__init__.py
wired/container.py
wired/decorators.py
wired/dataclasses/__init__.py
wired/dataclasses/decorators.py
wired/dataclasses/field_types.py
wired/dataclasses/injector.py
wired/dataclasses/models.py
wired/dataclasses/registration.py
wired-0.4.dist-info/LICENSE.txt
wired-0.4.dist-info/METADATA
wired-0.4.dist-info/WHEEL
wired-0.4.dist-info/top_level.txt
wired-0.4.dist-info/RECORD
