Metadata-Version: 2.1
Name: wired
Version: 0.4
Summary: An inversion-of-control (IoC) container for building decoupled, configurable, pluggable applications.
Home-page: https://github.com/mmerickel/wired
Author: Michael Merickel
Author-email: pylons-discuss@googlegroups.com
Project-URL: Documentation, https://wired.readthedocs.io
Project-URL: Changelog, https://wired.readthedocs.io/en/latest/changes.html
Project-URL: Issue Tracker, https://github.com/mmerickel/wired/issues
Keywords: ioc,inversion of control,dependency injection,service locator,singleton,service factory
Classifier: Development Status :: 4 - Beta
Classifier: Intended Audience :: Developers
Classifier: License :: OSI Approved :: MIT License
Classifier: Natural Language :: English
Classifier: Programming Language :: Python :: 3
Classifier: Programming Language :: Python :: 3.8
Classifier: Programming Language :: Python :: 3.9
Classifier: Programming Language :: Python :: 3.10
Classifier: Programming Language :: Python :: 3.11
Classifier: Programming Language :: Python :: 3.12
Classifier: Programming Language :: Python :: Implementation :: CPython
Classifier: Programming Language :: Python :: Implementation :: PyPy
Requires-Python: >=3.8
License-File: LICENSE.txt
Requires-Dist: zope.interface
Provides-Extra: docs
Requires-Dist: Sphinx ; extra == 'docs'
Requires-Dist: sphinx-rtd-theme ; extra == 'docs'
Requires-Dist: venusian ; extra == 'docs'
Provides-Extra: testing
Requires-Dist: pytest ; extra == 'testing'
Requires-Dist: pytest-cov ; extra == 'testing'
Requires-Dist: venusian ; extra == 'testing'
Requires-Dist: sybil ; extra == 'testing'
